MANIFEST.in
README.md
setup.py
tests/__init__.py
tests/unit/__init__.py
tests/unit/test_flutter.py
zmei_gen_flutter/__init__.py
zmei_gen_flutter.egg-info/PKG-INFO
zmei_gen_flutter.egg-info/SOURCES.txt
zmei_gen_flutter.egg-info/dependency_links.txt
zmei_gen_flutter.egg-info/entry_points.txt
zmei_gen_flutter.egg-info/requires.txt
zmei_gen_flutter.egg-info/top_level.txt
zmei_gen_flutter/extensions/__init__.py
zmei_gen_flutter/extensions/page/__init__.py
zmei_gen_flutter/extensions/page/flutter.py
zmei_gen_flutter/generator/__init__.py
zmei_gen_flutter/generator/flutter.py
zmei_gen_flutter/grammar/PageExtensionFlutter.g4
zmei_gen_flutter/grammar/__init__.py
zmei_gen_flutter/grammar/struct.py
zmei_gen_flutter/grammar/tokens.py
zmei_gen_flutter/parsers/__init__.py
zmei_gen_flutter/parsers/all_stage3.py
zmei_gen_flutter/templates/flutter.app.dart.tpl
zmei_gen_flutter/templates/flutter.cmp.menu.dart.tpl
zmei_gen_flutter/templates/flutter.main.dart.tpl
zmei_gen_flutter/templates/flutter.model.dart.tpl
zmei_gen_flutter/templates/flutter.page.dart.tpl
zmei_gen_flutter/templates/flutter.page.ui.dart.tpl
zmei_gen_flutter/templates/flutter.pubspec.yaml.tpl
zmei_gen_flutter/templates/flutter.routes.dart.tpl
zmei_gen_flutter/templates/flutter.state.dart.tpl
zmei_gen_flutter/templates/flutter.utils.dart.tpl