Metadata-Version: 1.0
Name: zmei-gen-flutter
Version: 0.1.3
Summary: FLutter generator for Zmei
Home-page: UNKNOWN
Author: Alex Rudakov
Author-email: ribozz@gmail.com
License: GPLv3
Platform: UNKNOWN
